wavefront_pyformance/__init__.py
wavefront_pyformance/delta.py
wavefront_pyformance/runtime_metrics.py
wavefront_pyformance/tagged_registry.py
wavefront_pyformance/wavefront_histogram.py
wavefront_pyformance/wavefront_reporter.py
wavefront_pyformance-1.2.4.dist-info/LICENSE
wavefront_pyformance-1.2.4.dist-info/METADATA
wavefront_pyformance-1.2.4.dist-info/WHEEL
wavefront_pyformance-1.2.4.dist-info/top_level.txt
wavefront_pyformance-1.2.4.dist-info/RECORD
