Metadata-Version: 2.1
Name: wavefront-pyformance
Version: 1.2.4
Summary: VMware Aria Operations for Applications Pyformance Library
Home-page: https://github.com/wavefrontHQ/wavefront-pyformance
Author: VMware Aria Operations for Applications Team
Author-email: chitimba@wavefront.com
License: Apache-2.0
Keywords: Distributed Tracing,Logging,Metrics,Monitoring,Observability,PyFormance,Tracing,Wavefront,Wavefront Pyformance
Classifier: Development Status :: 5 - Production/Stable
Classifier: Intended Audience :: Developers
Classifier: Intended Audience :: Information Technology
Classifier: Intended Audience :: System Administrators
Classifier: License :: OSI Approved :: Apache Software License
Classifier: Programming Language :: Python :: 3.8
Classifier: Programming Language :: Python :: 3.9
Classifier: Programming Language :: Python :: 3.10
Classifier: Programming Language :: Python :: 3.11
Classifier: Topic :: Software Development :: Libraries :: Python Modules
Classifier: Topic :: System :: Monitoring
Classifier: Topic :: System :: Networking :: Monitoring
License-File: LICENSE
Requires-Dist: pyformance >=0.4
Requires-Dist: wavefront-sdk-python >=1.8.0
Requires-Dist: psutil >=5.6.3
